gen_kernel_module/__init__.py
gen_kernel_module/py.typed
gen_kernel_module/conf/gen_kernel_module.cfg
gen_kernel_module/conf/gen_kernel_module.logo
gen_kernel_module/conf/gen_kernel_module_util.cfg
gen_kernel_module/conf/project.yaml
gen_kernel_module/conf/template/block/Makefile.template
gen_kernel_module/conf/template/block/lkm.template
gen_kernel_module/conf/template/block/test.template
gen_kernel_module/conf/template/char/Makefile.template
gen_kernel_module/conf/template/char/lkm.template
gen_kernel_module/conf/template/char/test.template
gen_kernel_module/conf/template/net/Makefile.template
gen_kernel_module/conf/template/net/lkm.template
gen_kernel_module/conf/template/net/test.template
gen_kernel_module/conf/template/vma/Makefile.template
gen_kernel_module/conf/template/vma/lkm.template
gen_kernel_module/conf/template/vma/test.template
gen_kernel_module/lkm/__init__.py
gen_kernel_module/lkm/read_template.py
gen_kernel_module/lkm/write_template.py
gen_kernel_module/log/gen_kernel_module.log
usr/local/bin/gen_kernel_module_run.py
gen_kernel_module-1.3.8.dist-info/LICENSE
gen_kernel_module-1.3.8.dist-info/METADATA
gen_kernel_module-1.3.8.dist-info/WHEEL
gen_kernel_module-1.3.8.dist-info/top_level.txt
gen_kernel_module-1.3.8.dist-info/RECORD
